pycparser/__init__.py
pycparser/_ast_gen.py
pycparser/_build_tables.py
pycparser/_c_ast.cfg
pycparser/ast_transforms.py
pycparser/c_ast.py
pycparser/c_generator.py
pycparser/c_lexer.py
pycparser/c_parser.py
pycparser/lextab.py
pycparser/plyparser.py
pycparser/yacctab.py
pycparser/__pycache__/__init__.cpython-34.pyc
pycparser/__pycache__/_ast_gen.cpython-34.pyc
pycparser/__pycache__/ast_transforms.cpython-34.pyc
pycparser/__pycache__/c_ast.cpython-34.pyc
pycparser/__pycache__/c_lexer.cpython-34.pyc
pycparser/__pycache__/c_parser.cpython-34.pyc
pycparser/__pycache__/lextab.cpython-34.pyc
pycparser/__pycache__/plyparser.cpython-34.pyc
pycparser/__pycache__/yacctab.cpython-34.pyc
pycparser/ply/__init__.py
pycparser/ply/cpp.py
pycparser/ply/ctokens.py
pycparser/ply/lex.py
pycparser/ply/yacc.py
pycparser/ply/__pycache__/__init__.cpython-34.pyc
pycparser/ply/__pycache__/lex.cpython-34.pyc
pycparser/ply/__pycache__/yacc.cpython-34.pyc
pycparser_plz_ignore-2.14.dist-info/DESCRIPTION.rst
pycparser_plz_ignore-2.14.dist-info/METADATA
pycparser_plz_ignore-2.14.dist-info/RECORD
pycparser_plz_ignore-2.14.dist-info/WHEEL
pycparser_plz_ignore-2.14.dist-info/metadata.json
pycparser_plz_ignore-2.14.dist-info/top_level.txt
