Metadata-Version: 2.0
Name: pycparser-plz-ignore
Version: 2.14
Summary: C parser in Python
Home-page: https://github.com/eliben/pycparser
Author: Eli Bendersky
Author-email: eliben@gmail.com
License: BSD
Platform: Cross Platform
Classifier: Programming Language :: Python :: 2
Classifier: Programming Language :: Python :: 3
